README.md
setup.py
StockAnalysisSystem/__init__.py
StockAnalysisSystem/api.py
StockAnalysisSystem/readme.py
StockAnalysisSystem.egg-info/PKG-INFO
StockAnalysisSystem.egg-info/SOURCES.txt
StockAnalysisSystem.egg-info/dependency_links.txt
StockAnalysisSystem.egg-info/requires.txt
StockAnalysisSystem.egg-info/top_level.txt
StockAnalysisSystem/core/DataHubEntry.py
StockAnalysisSystem/core/ExtensionEntry.py
StockAnalysisSystem/core/FactorEntry.py
StockAnalysisSystem/core/StockAnalysisSystem.py
StockAnalysisSystem/core/StrategyEntry.py
StockAnalysisSystem/core/__init__.py
StockAnalysisSystem/core/config.py
StockAnalysisSystem/core/DataHub/DataAgent.py
StockAnalysisSystem/core/DataHub/DataAgentBuilder.py
StockAnalysisSystem/core/DataHub/DataUtility.py
StockAnalysisSystem/core/DataHub/UniversalDataCenter.py
StockAnalysisSystem/core/DataHub/__init__.py
StockAnalysisSystem/core/Database/DatabaseEntry.py
StockAnalysisSystem/core/Database/NoSqlRw.py
StockAnalysisSystem/core/Database/SqlRw.py
StockAnalysisSystem/core/Database/UpdateTableEx.py
StockAnalysisSystem/core/Database/XListTable.py
StockAnalysisSystem/core/Database/__init__.py
StockAnalysisSystem/core/Utiltity/AnalyzerUtility.py
StockAnalysisSystem/core/Utiltity/CollectorUtility.py
StockAnalysisSystem/core/Utiltity/FactorUtility.py
StockAnalysisSystem/core/Utiltity/TableViewEx.py
StockAnalysisSystem/core/Utiltity/__init__.py
StockAnalysisSystem/core/Utiltity/common.py
StockAnalysisSystem/core/Utiltity/constant.py
StockAnalysisSystem/core/Utiltity/dependency.py
StockAnalysisSystem/core/Utiltity/df_utility.py
StockAnalysisSystem/core/Utiltity/digit_utility.py
StockAnalysisSystem/core/Utiltity/plugin_manager.py
StockAnalysisSystem/core/Utiltity/securities_selector.py
StockAnalysisSystem/core/Utiltity/task_queue.py
StockAnalysisSystem/core/Utiltity/time_utility.py
StockAnalysisSystem/core/Utiltity/ui_utility.py
StockAnalysisSystem/plugin/__init__.py
StockAnalysisSystem/plugin/Analyzer/__init__.py
StockAnalysisSystem/plugin/Analyzer/analyzer_tang.py
StockAnalysisSystem/plugin/Analyzer/basic_finance_analysis.py
StockAnalysisSystem/plugin/Analyzer/constant_analysis.py
StockAnalysisSystem/plugin/Analyzer/dummy_plugin_for_analyzer_test.py
