Metadata-Version: 1.2
Name: StockAnalysisSystem
Version: 0.0.7
Summary: Stock Analysis System
Home-page: https://gitee.com/SleepySoft/StockAnalysisSystem
Author: Sleepy
Author-email: sleepysoft@gmail.com
Maintainer: Sleepy
Maintainer-email: sleepysoft@gmail.com
License: Apache License
Keywords: stock analysis system sas
Platform: any
